{
  "login": "adauto6",
  "id": 17775642,
  "node_id": "MDQ6VXNlcjE3Nzc1NjQy",
  "avatar_url": "https://avatars.githubusercontent.com/u/17775642?v=4",
  "gravatar_id": "",
  "url": "https://api.github.com/users/adauto6",
  "html_url": "https://github.com/adauto6",
  "followers_url": "https://api.github.com/users/adauto6/followers",
  "following_url": "https://api.github.com/users/adauto6/following{/other_user}",
  "gists_url": "https://api.github.com/users/adauto6/gists{/gist_id}",
  "starred_url": "https://api.github.com/users/adauto6/starred{/owner}{/repo}",
  "subscriptions_url": "https://api.github.com/users/adauto6/subscriptions",
  "organizations_url": "https://api.github.com/users/adauto6/orgs",
  "repos_url": "https://api.github.com/users/adauto6/repos",
  "events_url": "https://api.github.com/users/adauto6/events{/privacy}",
  "received_events_url": "https://api.github.com/users/adauto6/received_events",
  "type": "User",
  "user_view_type": "public",
  "site_admin": false,
  "name": "T1t0",
  "company": null,
  "blog": "",
  "location": null,
  "email": null,
  "hireable": null,
  "bio": null,
  "twitter_username": null,
  "public_repos": 8,
  "public_gists": 0,
  "followers": 3,
  "following": 0,
  "created_at": "2016-03-11T02:53:11Z",
  "updated_at": "2022-03-01T19:26:29Z"
}