{
  "login": "AmAmIyA-Q",
  "id": 151153446,
  "node_id": "U_kgDOCQJrJg",
  "avatar_url": "https://avatars.githubusercontent.com/u/151153446?v=4",
  "gravatar_id": "",
  "url": "https://api.github.com/users/AmAmIyA-Q",
  "html_url": "https://github.com/AmAmIyA-Q",
  "followers_url": "https://api.github.com/users/AmAmIyA-Q/followers",
  "following_url": "https://api.github.com/users/AmAmIyA-Q/following{/other_user}",
  "gists_url": "https://api.github.com/users/AmAmIyA-Q/gists{/gist_id}",
  "starred_url": "https://api.github.com/users/AmAmIyA-Q/starred{/owner}{/repo}",
  "subscriptions_url": "https://api.github.com/users/AmAmIyA-Q/subscriptions",
  "organizations_url": "https://api.github.com/users/AmAmIyA-Q/orgs",
  "repos_url": "https://api.github.com/users/AmAmIyA-Q/repos",
  "events_url": "https://api.github.com/users/AmAmIyA-Q/events{/privacy}",
  "received_events_url": "https://api.github.com/users/AmAmIyA-Q/received_events",
  "type": "User",
  "user_view_type": "public",
  "site_admin": false,
  "name": "Guanju Yan",
  "company": "Shanghai Jiao Tong University",
  "blog": "",
  "location": "Shanghai",
  "email": "ygj2003@qq.com",
  "hireable": null,
  "bio": "Student in Shanghai Jiao Tong University majoring in physics",
  "twitter_username": null,
  "public_repos": 4,
  "public_gists": 0,
  "followers": 0,
  "following": 2,
  "created_at": "2023-11-17T10:59:18Z",
  "updated_at": "2024-10-24T12:11:15Z"
}