{
  "login": "AndrewOriani",
  "id": 32420759,
  "node_id": "MDQ6VXNlcjMyNDIwNzU5",
  "avatar_url": "https://avatars.githubusercontent.com/u/32420759?v=4",
  "gravatar_id": "",
  "url": "https://api.github.com/users/AndrewOriani",
  "html_url": "https://github.com/AndrewOriani",
  "followers_url": "https://api.github.com/users/AndrewOriani/followers",
  "following_url": "https://api.github.com/users/AndrewOriani/following{/other_user}",
  "gists_url": "https://api.github.com/users/AndrewOriani/gists{/gist_id}",
  "starred_url": "https://api.github.com/users/AndrewOriani/starred{/owner}{/repo}",
  "subscriptions_url": "https://api.github.com/users/AndrewOriani/subscriptions",
  "organizations_url": "https://api.github.com/users/AndrewOriani/orgs",
  "repos_url": "https://api.github.com/users/AndrewOriani/repos",
  "events_url": "https://api.github.com/users/AndrewOriani/events{/privacy}",
  "received_events_url": "https://api.github.com/users/AndrewOriani/received_events",
  "type": "User",
  "user_view_type": "public",
  "site_admin": false,
  "name": "Andrew Oriani",
  "company": "University of Chicago",
  "blog": "",
  "location": "Chicago, Illinois",
  "email": "oriani@uchicago.edu",
  "hireable": null,
  "bio": "PhD candidate at UChicago working with David Schuster (@SchusterLab). Applied cryogenics guru and engineer  researching 3D superconducting RF cavities for CQED.",
  "twitter_username": null,
  "public_repos": 8,
  "public_gists": 0,
  "followers": 15,
  "following": 3,
  "created_at": "2017-09-30T19:08:10Z",
  "updated_at": "2024-05-14T04:49:46Z"
}