{
  "login": "ankit-pn",
  "id": 61223051,
  "node_id": "MDQ6VXNlcjYxMjIzMDUx",
  "avatar_url": "https://avatars.githubusercontent.com/u/61223051?v=4",
  "gravatar_id": "",
  "url": "https://api.github.com/users/ankit-pn",
  "html_url": "https://github.com/ankit-pn",
  "followers_url": "https://api.github.com/users/ankit-pn/followers",
  "following_url": "https://api.github.com/users/ankit-pn/following{/other_user}",
  "gists_url": "https://api.github.com/users/ankit-pn/gists{/gist_id}",
  "starred_url": "https://api.github.com/users/ankit-pn/starred{/owner}{/repo}",
  "subscriptions_url": "https://api.github.com/users/ankit-pn/subscriptions",
  "organizations_url": "https://api.github.com/users/ankit-pn/orgs",
  "repos_url": "https://api.github.com/users/ankit-pn/repos",
  "events_url": "https://api.github.com/users/ankit-pn/events{/privacy}",
  "received_events_url": "https://api.github.com/users/ankit-pn/received_events",
  "type": "User",
  "user_view_type": "public",
  "site_admin": false,
  "name": "Ankit",
  "company": null,
  "blog": "",
  "location": "NIT, Bhopal",
  "email": null,
  "hireable": null,
  "bio": "Coffee & Code \ud83d\udc9c",
  "twitter_username": null,
  "public_repos": 76,
  "public_gists": 0,
  "followers": 37,
  "following": 97,
  "created_at": "2020-02-19T06:33:22Z",
  "updated_at": "2024-10-21T01:22:10Z"
}