{
  "login": "apcarrik",
  "id": 8772103,
  "node_id": "MDQ6VXNlcjg3NzIxMDM=",
  "avatar_url": "https://avatars.githubusercontent.com/u/8772103?v=4",
  "gravatar_id": "",
  "url": "https://api.github.com/users/apcarrik",
  "html_url": "https://github.com/apcarrik",
  "followers_url": "https://api.github.com/users/apcarrik/followers",
  "following_url": "https://api.github.com/users/apcarrik/following{/other_user}",
  "gists_url": "https://api.github.com/users/apcarrik/gists{/gist_id}",
  "starred_url": "https://api.github.com/users/apcarrik/starred{/owner}{/repo}",
  "subscriptions_url": "https://api.github.com/users/apcarrik/subscriptions",
  "organizations_url": "https://api.github.com/users/apcarrik/orgs",
  "repos_url": "https://api.github.com/users/apcarrik/repos",
  "events_url": "https://api.github.com/users/apcarrik/events{/privacy}",
  "received_events_url": "https://api.github.com/users/apcarrik/received_events",
  "type": "User",
  "user_view_type": "public",
  "site_admin": false,
  "name": "Adam Carriker",
  "company": null,
  "blog": "",
  "location": "Seattle, WA",
  "email": null,
  "hireable": null,
  "bio": "Software engineer working on quantum computing.",
  "twitter_username": null,
  "public_repos": 11,
  "public_gists": 0,
  "followers": 0,
  "following": 0,
  "created_at": "2014-09-15T00:16:58Z",
  "updated_at": "2024-02-12T03:58:35Z"
}