{
  "login": "arpitagrawal23",
  "id": 18568883,
  "node_id": "MDQ6VXNlcjE4NTY4ODgz",
  "avatar_url": "https://avatars.githubusercontent.com/u/18568883?v=4",
  "gravatar_id": "",
  "url": "https://api.github.com/users/arpitagrawal23",
  "html_url": "https://github.com/arpitagrawal23",
  "followers_url": "https://api.github.com/users/arpitagrawal23/followers",
  "following_url": "https://api.github.com/users/arpitagrawal23/following{/other_user}",
  "gists_url": "https://api.github.com/users/arpitagrawal23/gists{/gist_id}",
  "starred_url": "https://api.github.com/users/arpitagrawal23/starred{/owner}{/repo}",
  "subscriptions_url": "https://api.github.com/users/arpitagrawal23/subscriptions",
  "organizations_url": "https://api.github.com/users/arpitagrawal23/orgs",
  "repos_url": "https://api.github.com/users/arpitagrawal23/repos",
  "events_url": "https://api.github.com/users/arpitagrawal23/events{/privacy}",
  "received_events_url": "https://api.github.com/users/arpitagrawal23/received_events",
  "type": "User",
  "user_view_type": "public",
  "site_admin": false,
  "name": "Arpit Agrawal",
  "company": null,
  "blog": "https://www.linkedin.com/in/arpitagrawal23/",
  "location": "University of Maryland - College Park",
  "email": null,
  "hireable": null,
  "bio": null,
  "twitter_username": null,
  "public_repos": 1,
  "public_gists": 0,
  "followers": 0,
  "following": 0,
  "created_at": "2016-04-20T07:15:46Z",
  "updated_at": "2018-03-20T05:15:11Z"
}