{
  "login": "atithi8",
  "id": 36245272,
  "node_id": "MDQ6VXNlcjM2MjQ1Mjcy",
  "avatar_url": "https://avatars.githubusercontent.com/u/36245272?v=4",
  "gravatar_id": "",
  "url": "https://api.github.com/users/atithi8",
  "html_url": "https://github.com/atithi8",
  "followers_url": "https://api.github.com/users/atithi8/followers",
  "following_url": "https://api.github.com/users/atithi8/following{/other_user}",
  "gists_url": "https://api.github.com/users/atithi8/gists{/gist_id}",
  "starred_url": "https://api.github.com/users/atithi8/starred{/owner}{/repo}",
  "subscriptions_url": "https://api.github.com/users/atithi8/subscriptions",
  "organizations_url": "https://api.github.com/users/atithi8/orgs",
  "repos_url": "https://api.github.com/users/atithi8/repos",
  "events_url": "https://api.github.com/users/atithi8/events{/privacy}",
  "received_events_url": "https://api.github.com/users/atithi8/received_events",
  "type": "User",
  "user_view_type": "public",
  "site_admin": false,
  "name": "Atithi Acharya",
  "company": null,
  "blog": "atithi@github",
  "location": null,
  "email": null,
  "hireable": null,
  "bio": null,
  "twitter_username": null,
  "public_repos": 16,
  "public_gists": 0,
  "followers": 2,
  "following": 10,
  "created_at": "2018-02-07T20:57:21Z",
  "updated_at": "2024-10-28T21:49:22Z"
}