{
  "login": "audunn",
  "id": 3875306,
  "node_id": "MDQ6VXNlcjM4NzUzMDY=",
  "avatar_url": "https://avatars.githubusercontent.com/u/3875306?v=4",
  "gravatar_id": "",
  "url": "https://api.github.com/users/audunn",
  "html_url": "https://github.com/audunn",
  "followers_url": "https://api.github.com/users/audunn/followers",
  "following_url": "https://api.github.com/users/audunn/following{/other_user}",
  "gists_url": "https://api.github.com/users/audunn/gists{/gist_id}",
  "starred_url": "https://api.github.com/users/audunn/starred{/owner}{/repo}",
  "subscriptions_url": "https://api.github.com/users/audunn/subscriptions",
  "organizations_url": "https://api.github.com/users/audunn/orgs",
  "repos_url": "https://api.github.com/users/audunn/repos",
  "events_url": "https://api.github.com/users/audunn/events{/privacy}",
  "received_events_url": "https://api.github.com/users/audunn/received_events",
  "type": "User",
  "user_view_type": "public",
  "site_admin": false,
  "name": "Au\u00f0unn",
  "company": "NetApp",
  "blog": "https://xn--lofll-1sat.is/@audunn",
  "location": "Iceland",
  "email": "Audunn.Baldvinsson@netapp.com",
  "hireable": null,
  "bio": "Software developer, cloud infrastructure, fintech professionally but dabble in some other stuff",
  "twitter_username": null,
  "public_repos": 16,
  "public_gists": 0,
  "followers": 3,
  "following": 1,
  "created_at": "2013-03-15T13:53:29Z",
  "updated_at": "2024-07-04T23:03:19Z"
}