{
  "login": "automagicaly",
  "id": 10888054,
  "node_id": "MDQ6VXNlcjEwODg4MDU0",
  "avatar_url": "https://avatars.githubusercontent.com/u/10888054?v=4",
  "gravatar_id": "",
  "url": "https://api.github.com/users/automagicaly",
  "html_url": "https://github.com/automagicaly",
  "followers_url": "https://api.github.com/users/automagicaly/followers",
  "following_url": "https://api.github.com/users/automagicaly/following{/other_user}",
  "gists_url": "https://api.github.com/users/automagicaly/gists{/gist_id}",
  "starred_url": "https://api.github.com/users/automagicaly/starred{/owner}{/repo}",
  "subscriptions_url": "https://api.github.com/users/automagicaly/subscriptions",
  "organizations_url": "https://api.github.com/users/automagicaly/orgs",
  "repos_url": "https://api.github.com/users/automagicaly/repos",
  "events_url": "https://api.github.com/users/automagicaly/events{/privacy}",
  "received_events_url": "https://api.github.com/users/automagicaly/received_events",
  "type": "User",
  "user_view_type": "public",
  "site_admin": false,
  "name": "Renan Lordello de Aguiar",
  "company": "Amazon",
  "blog": "",
  "location": "S\u00e3o Paulo, Brazil",
  "email": "renan.lord.de.aguiar@gmail.com",
  "hireable": null,
  "bio": "Software Engineer",
  "twitter_username": null,
  "public_repos": 13,
  "public_gists": 6,
  "followers": 20,
  "following": 11,
  "created_at": "2015-02-06T20:15:35Z",
  "updated_at": "2024-10-30T11:18:10Z"
}