{
  "login": "boricles",
  "id": 424047,
  "node_id": "MDQ6VXNlcjQyNDA0Nw==",
  "avatar_url": "https://avatars.githubusercontent.com/u/424047?v=4",
  "gravatar_id": "",
  "url": "https://api.github.com/users/boricles",
  "html_url": "https://github.com/boricles",
  "followers_url": "https://api.github.com/users/boricles/followers",
  "following_url": "https://api.github.com/users/boricles/following{/other_user}",
  "gists_url": "https://api.github.com/users/boricles/gists{/gist_id}",
  "starred_url": "https://api.github.com/users/boricles/starred{/owner}{/repo}",
  "subscriptions_url": "https://api.github.com/users/boricles/subscriptions",
  "organizations_url": "https://api.github.com/users/boricles/orgs",
  "repos_url": "https://api.github.com/users/boricles/repos",
  "events_url": "https://api.github.com/users/boricles/events{/privacy}",
  "received_events_url": "https://api.github.com/users/boricles/received_events",
  "type": "User",
  "user_view_type": "public",
  "site_admin": false,
  "name": "Boris Villaz\u00f3n-Terrazas",
  "company": null,
  "blog": "https://github.com/boricles",
  "location": null,
  "email": "boricles@gmail.com",
  "hireable": null,
  "bio": null,
  "twitter_username": null,
  "public_repos": 36,
  "public_gists": 0,
  "followers": 19,
  "following": 8,
  "created_at": "2010-10-01T23:26:29Z",
  "updated_at": "2023-04-12T23:36:59Z"
}