{
  "login": "dasanind",
  "id": 3979909,
  "node_id": "MDQ6VXNlcjM5Nzk5MDk=",
  "avatar_url": "https://avatars.githubusercontent.com/u/3979909?v=4",
  "gravatar_id": "",
  "url": "https://api.github.com/users/dasanind",
  "html_url": "https://github.com/dasanind",
  "followers_url": "https://api.github.com/users/dasanind/followers",
  "following_url": "https://api.github.com/users/dasanind/following{/other_user}",
  "gists_url": "https://api.github.com/users/dasanind/gists{/gist_id}",
  "starred_url": "https://api.github.com/users/dasanind/starred{/owner}{/repo}",
  "subscriptions_url": "https://api.github.com/users/dasanind/subscriptions",
  "organizations_url": "https://api.github.com/users/dasanind/orgs",
  "repos_url": "https://api.github.com/users/dasanind/repos",
  "events_url": "https://api.github.com/users/dasanind/events{/privacy}",
  "received_events_url": "https://api.github.com/users/dasanind/received_events",
  "type": "User",
  "user_view_type": "public",
  "site_admin": false,
  "name": "Anindita Das",
  "company": null,
  "blog": "https://www.linkedin.com/in/anindita-das-934328b/",
  "location": "Gainesville, FL",
  "email": null,
  "hireable": null,
  "bio": "Passionate, self-motivated and quick learner. I love to solve complex software problems, to build applications and to travel around the world.",
  "twitter_username": null,
  "public_repos": 23,
  "public_gists": 0,
  "followers": 0,
  "following": 3,
  "created_at": "2013-03-26T23:22:11Z",
  "updated_at": "2024-10-24T19:44:46Z"
}