{
  "login": "Davidelanz",
  "id": 22351903,
  "node_id": "MDQ6VXNlcjIyMzUxOTAz",
  "avatar_url": "https://avatars.githubusercontent.com/u/22351903?v=4",
  "gravatar_id": "",
  "url": "https://api.github.com/users/Davidelanz",
  "html_url": "https://github.com/Davidelanz",
  "followers_url": "https://api.github.com/users/Davidelanz/followers",
  "following_url": "https://api.github.com/users/Davidelanz/following{/other_user}",
  "gists_url": "https://api.github.com/users/Davidelanz/gists{/gist_id}",
  "starred_url": "https://api.github.com/users/Davidelanz/starred{/owner}{/repo}",
  "subscriptions_url": "https://api.github.com/users/Davidelanz/subscriptions",
  "organizations_url": "https://api.github.com/users/Davidelanz/orgs",
  "repos_url": "https://api.github.com/users/Davidelanz/repos",
  "events_url": "https://api.github.com/users/Davidelanz/events{/privacy}",
  "received_events_url": "https://api.github.com/users/Davidelanz/received_events",
  "type": "User",
  "user_view_type": "public",
  "site_admin": false,
  "name": "Davide Lanza",
  "company": "@eikonproject",
  "blog": "dev.davidelanza.it",
  "location": "Hamburg",
  "email": "info@davidelanza.it",
  "hireable": null,
  "bio": "Software Engineer, Robotics MsC",
  "twitter_username": null,
  "public_repos": 27,
  "public_gists": 3,
  "followers": 21,
  "following": 25,
  "created_at": "2016-09-21T17:17:34Z",
  "updated_at": "2024-09-19T18:09:34Z"
}