{
  "login": "deji725",
  "id": 17463680,
  "node_id": "MDQ6VXNlcjE3NDYzNjgw",
  "avatar_url": "https://avatars.githubusercontent.com/u/17463680?v=4",
  "gravatar_id": "",
  "url": "https://api.github.com/users/deji725",
  "html_url": "https://github.com/deji725",
  "followers_url": "https://api.github.com/users/deji725/followers",
  "following_url": "https://api.github.com/users/deji725/following{/other_user}",
  "gists_url": "https://api.github.com/users/deji725/gists{/gist_id}",
  "starred_url": "https://api.github.com/users/deji725/starred{/owner}{/repo}",
  "subscriptions_url": "https://api.github.com/users/deji725/subscriptions",
  "organizations_url": "https://api.github.com/users/deji725/orgs",
  "repos_url": "https://api.github.com/users/deji725/repos",
  "events_url": "https://api.github.com/users/deji725/events{/privacy}",
  "received_events_url": "https://api.github.com/users/deji725/received_events",
  "type": "User",
  "user_view_type": "public",
  "site_admin": false,
  "name": "Deji Oyerinde",
  "company": "@mechadogs @AllStarCodeOrg",
  "blog": "",
  "location": null,
  "email": null,
  "hireable": null,
  "bio": null,
  "twitter_username": null,
  "public_repos": 43,
  "public_gists": 0,
  "followers": 1,
  "following": 3,
  "created_at": "2016-02-25T00:28:01Z",
  "updated_at": "2024-04-09T11:17:07Z"
}