{
  "login": "FabianBrings",
  "id": 151436989,
  "node_id": "U_kgDOCQa-vQ",
  "avatar_url": "https://avatars.githubusercontent.com/u/151436989?v=4",
  "gravatar_id": "",
  "url": "https://api.github.com/users/FabianBrings",
  "html_url": "https://github.com/FabianBrings",
  "followers_url": "https://api.github.com/users/FabianBrings/followers",
  "following_url": "https://api.github.com/users/FabianBrings/following{/other_user}",
  "gists_url": "https://api.github.com/users/FabianBrings/gists{/gist_id}",
  "starred_url": "https://api.github.com/users/FabianBrings/starred{/owner}{/repo}",
  "subscriptions_url": "https://api.github.com/users/FabianBrings/subscriptions",
  "organizations_url": "https://api.github.com/users/FabianBrings/orgs",
  "repos_url": "https://api.github.com/users/FabianBrings/repos",
  "events_url": "https://api.github.com/users/FabianBrings/events{/privacy}",
  "received_events_url": "https://api.github.com/users/FabianBrings/received_events",
  "type": "User",
  "user_view_type": "public",
  "site_admin": false,
  "name": "Fabian Brings",
  "company": "Bechtle GmbH & Co. KG",
  "blog": "",
  "location": null,
  "email": null,
  "hireable": null,
  "bio": null,
  "twitter_username": null,
  "public_repos": 1,
  "public_gists": 0,
  "followers": 0,
  "following": 0,
  "created_at": "2023-11-19T10:45:32Z",
  "updated_at": "2024-10-30T08:52:28Z"
}