{
  "login": "fernandodelaiglesia",
  "id": 14274350,
  "node_id": "MDQ6VXNlcjE0Mjc0MzUw",
  "avatar_url": "https://avatars.githubusercontent.com/u/14274350?v=4",
  "gravatar_id": "",
  "url": "https://api.github.com/users/fernandodelaiglesia",
  "html_url": "https://github.com/fernandodelaiglesia",
  "followers_url": "https://api.github.com/users/fernandodelaiglesia/followers",
  "following_url": "https://api.github.com/users/fernandodelaiglesia/following{/other_user}",
  "gists_url": "https://api.github.com/users/fernandodelaiglesia/gists{/gist_id}",
  "starred_url": "https://api.github.com/users/fernandodelaiglesia/starred{/owner}{/repo}",
  "subscriptions_url": "https://api.github.com/users/fernandodelaiglesia/subscriptions",
  "organizations_url": "https://api.github.com/users/fernandodelaiglesia/orgs",
  "repos_url": "https://api.github.com/users/fernandodelaiglesia/repos",
  "events_url": "https://api.github.com/users/fernandodelaiglesia/events{/privacy}",
  "received_events_url": "https://api.github.com/users/fernandodelaiglesia/received_events",
  "type": "User",
  "user_view_type": "public",
  "site_admin": false,
  "name": "Fernando",
  "company": null,
  "blog": "",
  "location": "Madrid",
  "email": null,
  "hireable": null,
  "bio": null,
  "twitter_username": null,
  "public_repos": 14,
  "public_gists": 0,
  "followers": 0,
  "following": 0,
  "created_at": "2015-09-14T11:54:24Z",
  "updated_at": "2023-10-03T13:40:46Z"
}