{
  "login": "gawelk",
  "id": 26271776,
  "node_id": "MDQ6VXNlcjI2MjcxNzc2",
  "avatar_url": "https://avatars.githubusercontent.com/u/26271776?v=4",
  "gravatar_id": "",
  "url": "https://api.github.com/users/gawelk",
  "html_url": "https://github.com/gawelk",
  "followers_url": "https://api.github.com/users/gawelk/followers",
  "following_url": "https://api.github.com/users/gawelk/following{/other_user}",
  "gists_url": "https://api.github.com/users/gawelk/gists{/gist_id}",
  "starred_url": "https://api.github.com/users/gawelk/starred{/owner}{/repo}",
  "subscriptions_url": "https://api.github.com/users/gawelk/subscriptions",
  "organizations_url": "https://api.github.com/users/gawelk/orgs",
  "repos_url": "https://api.github.com/users/gawelk/repos",
  "events_url": "https://api.github.com/users/gawelk/events{/privacy}",
  "received_events_url": "https://api.github.com/users/gawelk/received_events",
  "type": "User",
  "user_view_type": "public",
  "site_admin": false,
  "name": "Gawel Kus",
  "company": "Brown University",
  "blog": "",
  "location": "Providence, RI",
  "email": "gawel_kus@brown.edu",
  "hireable": null,
  "bio": null,
  "twitter_username": null,
  "public_repos": 9,
  "public_gists": 0,
  "followers": 1,
  "following": 2,
  "created_at": "2017-03-08T08:32:42Z",
  "updated_at": "2024-10-11T11:37:33Z"
}