{
  "login": "jackhyder",
  "id": 22288336,
  "node_id": "MDQ6VXNlcjIyMjg4MzM2",
  "avatar_url": "https://avatars.githubusercontent.com/u/22288336?v=4",
  "gravatar_id": "",
  "url": "https://api.github.com/users/jackhyder",
  "html_url": "https://github.com/jackhyder",
  "followers_url": "https://api.github.com/users/jackhyder/followers",
  "following_url": "https://api.github.com/users/jackhyder/following{/other_user}",
  "gists_url": "https://api.github.com/users/jackhyder/gists{/gist_id}",
  "starred_url": "https://api.github.com/users/jackhyder/starred{/owner}{/repo}",
  "subscriptions_url": "https://api.github.com/users/jackhyder/subscriptions",
  "organizations_url": "https://api.github.com/users/jackhyder/orgs",
  "repos_url": "https://api.github.com/users/jackhyder/repos",
  "events_url": "https://api.github.com/users/jackhyder/events{/privacy}",
  "received_events_url": "https://api.github.com/users/jackhyder/received_events",
  "type": "User",
  "user_view_type": "public",
  "site_admin": false,
  "name": "Jack Hyder",
  "company": null,
  "blog": "",
  "location": null,
  "email": "jackhyder20@gmail.com",
  "hireable": null,
  "bio": null,
  "twitter_username": null,
  "public_repos": 8,
  "public_gists": 2,
  "followers": 1,
  "following": 0,
  "created_at": "2016-09-19T06:46:06Z",
  "updated_at": "2022-12-02T17:23:46Z"
}