{
  "login": "JamesB-1qbit",
  "id": 84878946,
  "node_id": "MDQ6VXNlcjg0ODc4OTQ2",
  "avatar_url": "https://avatars.githubusercontent.com/u/84878946?v=4",
  "gravatar_id": "",
  "url": "https://api.github.com/users/JamesB-1qbit",
  "html_url": "https://github.com/JamesB-1qbit",
  "followers_url": "https://api.github.com/users/JamesB-1qbit/followers",
  "following_url": "https://api.github.com/users/JamesB-1qbit/following{/other_user}",
  "gists_url": "https://api.github.com/users/JamesB-1qbit/gists{/gist_id}",
  "starred_url": "https://api.github.com/users/JamesB-1qbit/starred{/owner}{/repo}",
  "subscriptions_url": "https://api.github.com/users/JamesB-1qbit/subscriptions",
  "organizations_url": "https://api.github.com/users/JamesB-1qbit/orgs",
  "repos_url": "https://api.github.com/users/JamesB-1qbit/repos",
  "events_url": "https://api.github.com/users/JamesB-1qbit/events{/privacy}",
  "received_events_url": "https://api.github.com/users/JamesB-1qbit/received_events",
  "type": "User",
  "site_admin": false,
  "name": "James Brown",
  "company": "Good Chemistry Company @goodchemistryco",
  "blog": "",
  "location": null,
  "email": null,
  "hireable": null,
  "bio": null,
  "twitter_username": null,
  "public_repos": 2,
  "public_gists": 0,
  "followers": 0,
  "following": 1,
  "created_at": "2021-05-26T21:41:12Z",
  "updated_at": "2023-10-05T16:05:52Z"
}