{
  "login": "jessding",
  "id": 49802382,
  "node_id": "MDQ6VXNlcjQ5ODAyMzgy",
  "avatar_url": "https://avatars.githubusercontent.com/u/49802382?v=4",
  "gravatar_id": "",
  "url": "https://api.github.com/users/jessding",
  "html_url": "https://github.com/jessding",
  "followers_url": "https://api.github.com/users/jessding/followers",
  "following_url": "https://api.github.com/users/jessding/following{/other_user}",
  "gists_url": "https://api.github.com/users/jessding/gists{/gist_id}",
  "starred_url": "https://api.github.com/users/jessding/starred{/owner}{/repo}",
  "subscriptions_url": "https://api.github.com/users/jessding/subscriptions",
  "organizations_url": "https://api.github.com/users/jessding/orgs",
  "repos_url": "https://api.github.com/users/jessding/repos",
  "events_url": "https://api.github.com/users/jessding/events{/privacy}",
  "received_events_url": "https://api.github.com/users/jessding/received_events",
  "type": "User",
  "user_view_type": "public",
  "site_admin": false,
  "name": "Jessica Ding",
  "company": null,
  "blog": "jessding.com",
  "location": "Cambridge, MA",
  "email": "jessding@mit.edu",
  "hireable": true,
  "bio": "@mit Computer Science/Electrical Engineering + Mathematics",
  "twitter_username": null,
  "public_repos": 9,
  "public_gists": 1,
  "followers": 24,
  "following": 12,
  "created_at": "2019-04-20T03:38:23Z",
  "updated_at": "2024-10-09T11:51:07Z"
}