{
  "login": "jlatone",
  "id": 676063,
  "node_id": "MDQ6VXNlcjY3NjA2Mw==",
  "avatar_url": "https://avatars.githubusercontent.com/u/676063?v=4",
  "gravatar_id": "",
  "url": "https://api.github.com/users/jlatone",
  "html_url": "https://github.com/jlatone",
  "followers_url": "https://api.github.com/users/jlatone/followers",
  "following_url": "https://api.github.com/users/jlatone/following{/other_user}",
  "gists_url": "https://api.github.com/users/jlatone/gists{/gist_id}",
  "starred_url": "https://api.github.com/users/jlatone/starred{/owner}{/repo}",
  "subscriptions_url": "https://api.github.com/users/jlatone/subscriptions",
  "organizations_url": "https://api.github.com/users/jlatone/orgs",
  "repos_url": "https://api.github.com/users/jlatone/repos",
  "events_url": "https://api.github.com/users/jlatone/events{/privacy}",
  "received_events_url": "https://api.github.com/users/jlatone/received_events",
  "type": "User",
  "user_view_type": "public",
  "site_admin": false,
  "name": "Joe Latone",
  "company": "IBM Research",
  "blog": "",
  "location": "San Francisco, CA",
  "email": "jlatone@us.ibm.com",
  "hireable": null,
  "bio": "Joe Latone (personal account using IBM email address)",
  "twitter_username": null,
  "public_repos": 9,
  "public_gists": 0,
  "followers": 4,
  "following": 0,
  "created_at": "2011-03-17T22:27:20Z",
  "updated_at": "2022-09-15T00:25:19Z"
}