{
  "login": "jongio",
  "id": 2163001,
  "node_id": "MDQ6VXNlcjIxNjMwMDE=",
  "avatar_url": "https://avatars.githubusercontent.com/u/2163001?v=4",
  "gravatar_id": "",
  "url": "https://api.github.com/users/jongio",
  "html_url": "https://github.com/jongio",
  "followers_url": "https://api.github.com/users/jongio/followers",
  "following_url": "https://api.github.com/users/jongio/following{/other_user}",
  "gists_url": "https://api.github.com/users/jongio/gists{/gist_id}",
  "starred_url": "https://api.github.com/users/jongio/starred{/owner}{/repo}",
  "subscriptions_url": "https://api.github.com/users/jongio/subscriptions",
  "organizations_url": "https://api.github.com/users/jongio/orgs",
  "repos_url": "https://api.github.com/users/jongio/repos",
  "events_url": "https://api.github.com/users/jongio/events{/privacy}",
  "received_events_url": "https://api.github.com/users/jongio/received_events",
  "type": "User",
  "user_view_type": "public",
  "site_admin": false,
  "name": "Jon Gallant",
  "company": "Microsoft",
  "blog": "http://jongallant.com",
  "location": "Seattle, WA",
  "email": null,
  "hireable": null,
  "bio": "Azure Developer Experience Architect",
  "twitter_username": "jongallant",
  "public_repos": 286,
  "public_gists": 88,
  "followers": 327,
  "following": 13,
  "created_at": "2012-08-16T12:38:10Z",
  "updated_at": "2024-10-02T11:21:59Z"
}