{
  "login": "kaitlinmgili",
  "id": 40485018,
  "node_id": "MDQ6VXNlcjQwNDg1MDE4",
  "avatar_url": "https://avatars.githubusercontent.com/u/40485018?v=4",
  "gravatar_id": "",
  "url": "https://api.github.com/users/kaitlinmgili",
  "html_url": "https://github.com/kaitlinmgili",
  "followers_url": "https://api.github.com/users/kaitlinmgili/followers",
  "following_url": "https://api.github.com/users/kaitlinmgili/following{/other_user}",
  "gists_url": "https://api.github.com/users/kaitlinmgili/gists{/gist_id}",
  "starred_url": "https://api.github.com/users/kaitlinmgili/starred{/owner}{/repo}",
  "subscriptions_url": "https://api.github.com/users/kaitlinmgili/subscriptions",
  "organizations_url": "https://api.github.com/users/kaitlinmgili/orgs",
  "repos_url": "https://api.github.com/users/kaitlinmgili/repos",
  "events_url": "https://api.github.com/users/kaitlinmgili/events{/privacy}",
  "received_events_url": "https://api.github.com/users/kaitlinmgili/received_events",
  "type": "User",
  "site_admin": false,
  "name": null,
  "company": null,
  "blog": "",
  "location": null,
  "email": null,
  "hireable": null,
  "bio": null,
  "twitter_username": null,
  "public_repos": 8,
  "public_gists": 0,
  "followers": 2,
  "following": 1,
  "created_at": "2018-06-22T06:40:59Z",
  "updated_at": "2024-06-12T17:08:13Z"
}