{
  "login": "leepike",
  "id": 406725,
  "node_id": "MDQ6VXNlcjQwNjcyNQ==",
  "avatar_url": "https://avatars.githubusercontent.com/u/406725?v=4",
  "gravatar_id": "",
  "url": "https://api.github.com/users/leepike",
  "html_url": "https://github.com/leepike",
  "followers_url": "https://api.github.com/users/leepike/followers",
  "following_url": "https://api.github.com/users/leepike/following{/other_user}",
  "gists_url": "https://api.github.com/users/leepike/gists{/gist_id}",
  "starred_url": "https://api.github.com/users/leepike/starred{/owner}{/repo}",
  "subscriptions_url": "https://api.github.com/users/leepike/subscriptions",
  "organizations_url": "https://api.github.com/users/leepike/orgs",
  "repos_url": "https://api.github.com/users/leepike/repos",
  "events_url": "https://api.github.com/users/leepike/events{/privacy}",
  "received_events_url": "https://api.github.com/users/leepike/received_events",
  "type": "User",
  "user_view_type": "public",
  "site_admin": false,
  "name": "Lee Pike",
  "company": null,
  "blog": "https://leepike.github.io/",
  "location": "Portland, Oregon, USA",
  "email": "leepike@gmail.com",
  "hireable": null,
  "bio": null,
  "twitter_username": null,
  "public_repos": 25,
  "public_gists": 11,
  "followers": 130,
  "following": 16,
  "created_at": "2010-09-19T06:06:37Z",
  "updated_at": "2024-10-01T11:20:35Z"
}