{
  "login": "lneuhaus",
  "id": 18272943,
  "node_id": "MDQ6VXNlcjE4MjcyOTQz",
  "avatar_url": "https://avatars.githubusercontent.com/u/18272943?v=4",
  "gravatar_id": "",
  "url": "https://api.github.com/users/lneuhaus",
  "html_url": "https://github.com/lneuhaus",
  "followers_url": "https://api.github.com/users/lneuhaus/followers",
  "following_url": "https://api.github.com/users/lneuhaus/following{/other_user}",
  "gists_url": "https://api.github.com/users/lneuhaus/gists{/gist_id}",
  "starred_url": "https://api.github.com/users/lneuhaus/starred{/owner}{/repo}",
  "subscriptions_url": "https://api.github.com/users/lneuhaus/subscriptions",
  "organizations_url": "https://api.github.com/users/lneuhaus/orgs",
  "repos_url": "https://api.github.com/users/lneuhaus/repos",
  "events_url": "https://api.github.com/users/lneuhaus/events{/privacy}",
  "received_events_url": "https://api.github.com/users/lneuhaus/received_events",
  "type": "User",
  "user_view_type": "public",
  "site_admin": false,
  "name": null,
  "company": null,
  "blog": "",
  "location": null,
  "email": null,
  "hireable": null,
  "bio": null,
  "twitter_username": null,
  "public_repos": 65,
  "public_gists": 0,
  "followers": 34,
  "following": 44,
  "created_at": "2016-04-04T22:26:26Z",
  "updated_at": "2024-10-28T18:54:51Z"
}