{
  "login": "marwahaha",
  "id": 2541209,
  "node_id": "MDQ6VXNlcjI1NDEyMDk=",
  "avatar_url": "https://avatars.githubusercontent.com/u/2541209?v=4",
  "gravatar_id": "",
  "url": "https://api.github.com/users/marwahaha",
  "html_url": "https://github.com/marwahaha",
  "followers_url": "https://api.github.com/users/marwahaha/followers",
  "following_url": "https://api.github.com/users/marwahaha/following{/other_user}",
  "gists_url": "https://api.github.com/users/marwahaha/gists{/gist_id}",
  "starred_url": "https://api.github.com/users/marwahaha/starred{/owner}{/repo}",
  "subscriptions_url": "https://api.github.com/users/marwahaha/subscriptions",
  "organizations_url": "https://api.github.com/users/marwahaha/orgs",
  "repos_url": "https://api.github.com/users/marwahaha/repos",
  "events_url": "https://api.github.com/users/marwahaha/events{/privacy}",
  "received_events_url": "https://api.github.com/users/marwahaha/received_events",
  "type": "User",
  "site_admin": false,
  "name": "Kunal Marwaha",
  "company": null,
  "blog": "kunalmarwaha.com/about",
  "location": "Chicago, IL",
  "email": "marwahaha@berkeley.edu",
  "hireable": null,
  "bio": null,
  "twitter_username": null,
  "public_repos": 1200,
  "public_gists": 21,
  "followers": 154,
  "following": 8,
  "created_at": "2012-10-12T01:30:18Z",
  "updated_at": "2024-08-22T18:50:59Z"
}