{
  "login": "MicrohexHQ",
  "id": 52498504,
  "node_id": "MDQ6VXNlcjUyNDk4NTA0",
  "avatar_url": "https://avatars.githubusercontent.com/u/52498504?v=4",
  "gravatar_id": "",
  "url": "https://api.github.com/users/MicrohexHQ",
  "html_url": "https://github.com/MicrohexHQ",
  "followers_url": "https://api.github.com/users/MicrohexHQ/followers",
  "following_url": "https://api.github.com/users/MicrohexHQ/following{/other_user}",
  "gists_url": "https://api.github.com/users/MicrohexHQ/gists{/gist_id}",
  "starred_url": "https://api.github.com/users/MicrohexHQ/starred{/owner}{/repo}",
  "subscriptions_url": "https://api.github.com/users/MicrohexHQ/subscriptions",
  "organizations_url": "https://api.github.com/users/MicrohexHQ/orgs",
  "repos_url": "https://api.github.com/users/MicrohexHQ/repos",
  "events_url": "https://api.github.com/users/MicrohexHQ/events{/privacy}",
  "received_events_url": "https://api.github.com/users/MicrohexHQ/received_events",
  "type": "User",
  "user_view_type": "public",
  "site_admin": false,
  "name": "hexunitechno",
  "company": null,
  "blog": "twitter.com/hexunitechno",
  "location": "Royaume Uni des Pays-Bas | EU",
  "email": null,
  "hireable": null,
  "bio": null,
  "twitter_username": null,
  "public_repos": 766,
  "public_gists": 23,
  "followers": 29,
  "following": 507,
  "created_at": "2019-07-03T13:34:20Z",
  "updated_at": "2019-11-20T06:51:11Z"
}