{
  "login": "mlaguna10",
  "id": 15188655,
  "node_id": "MDQ6VXNlcjE1MTg4NjU1",
  "avatar_url": "https://avatars.githubusercontent.com/u/15188655?v=4",
  "gravatar_id": "",
  "url": "https://api.github.com/users/mlaguna10",
  "html_url": "https://github.com/mlaguna10",
  "followers_url": "https://api.github.com/users/mlaguna10/followers",
  "following_url": "https://api.github.com/users/mlaguna10/following{/other_user}",
  "gists_url": "https://api.github.com/users/mlaguna10/gists{/gist_id}",
  "starred_url": "https://api.github.com/users/mlaguna10/starred{/owner}{/repo}",
  "subscriptions_url": "https://api.github.com/users/mlaguna10/subscriptions",
  "organizations_url": "https://api.github.com/users/mlaguna10/orgs",
  "repos_url": "https://api.github.com/users/mlaguna10/repos",
  "events_url": "https://api.github.com/users/mlaguna10/events{/privacy}",
  "received_events_url": "https://api.github.com/users/mlaguna10/received_events",
  "type": "User",
  "user_view_type": "public",
  "site_admin": false,
  "name": "Mateo Laguna",
  "company": null,
  "blog": "",
  "location": "Bogot\u00e1, Colombia.",
  "email": "m.laguna10@uniandes.edu.co",
  "hireable": null,
  "bio": "Physicist.\r\nComputing and Systems Engineer.\r\nUniandes.",
  "twitter_username": null,
  "public_repos": 31,
  "public_gists": 0,
  "followers": 2,
  "following": 2,
  "created_at": "2015-10-19T03:21:12Z",
  "updated_at": "2024-02-14T14:42:36Z"
}