{
  "login": "mlazzarin",
  "id": 48728634,
  "node_id": "MDQ6VXNlcjQ4NzI4NjM0",
  "avatar_url": "https://avatars.githubusercontent.com/u/48728634?v=4",
  "gravatar_id": "",
  "url": "https://api.github.com/users/mlazzarin",
  "html_url": "https://github.com/mlazzarin",
  "followers_url": "https://api.github.com/users/mlazzarin/followers",
  "following_url": "https://api.github.com/users/mlazzarin/following{/other_user}",
  "gists_url": "https://api.github.com/users/mlazzarin/gists{/gist_id}",
  "starred_url": "https://api.github.com/users/mlazzarin/starred{/owner}{/repo}",
  "subscriptions_url": "https://api.github.com/users/mlazzarin/subscriptions",
  "organizations_url": "https://api.github.com/users/mlazzarin/orgs",
  "repos_url": "https://api.github.com/users/mlazzarin/repos",
  "events_url": "https://api.github.com/users/mlazzarin/events{/privacy}",
  "received_events_url": "https://api.github.com/users/mlazzarin/received_events",
  "type": "User",
  "user_view_type": "public",
  "site_admin": false,
  "name": "Marco Lazzarin",
  "company": "Business Integration Partners",
  "blog": "",
  "location": "Milan, Italy",
  "email": null,
  "hireable": null,
  "bio": "Data Science consultant with a background in Physics. Always looking for new challenges.",
  "twitter_username": null,
  "public_repos": 1,
  "public_gists": 1,
  "followers": 7,
  "following": 4,
  "created_at": "2019-03-19T16:36:30Z",
  "updated_at": "2024-07-22T09:37:03Z"
}