{
  "login": "mlodi-hqs",
  "id": 108724576,
  "node_id": "U_kgDOBnsBYA",
  "avatar_url": "https://avatars.githubusercontent.com/u/108724576?v=4",
  "gravatar_id": "",
  "url": "https://api.github.com/users/mlodi-hqs",
  "html_url": "https://github.com/mlodi-hqs",
  "followers_url": "https://api.github.com/users/mlodi-hqs/followers",
  "following_url": "https://api.github.com/users/mlodi-hqs/following{/other_user}",
  "gists_url": "https://api.github.com/users/mlodi-hqs/gists{/gist_id}",
  "starred_url": "https://api.github.com/users/mlodi-hqs/starred{/owner}{/repo}",
  "subscriptions_url": "https://api.github.com/users/mlodi-hqs/subscriptions",
  "organizations_url": "https://api.github.com/users/mlodi-hqs/orgs",
  "repos_url": "https://api.github.com/users/mlodi-hqs/repos",
  "events_url": "https://api.github.com/users/mlodi-hqs/events{/privacy}",
  "received_events_url": "https://api.github.com/users/mlodi-hqs/received_events",
  "type": "User",
  "user_view_type": "public",
  "site_admin": false,
  "name": "Matteo Lodi",
  "company": "HQS Quantum Simulations",
  "blog": "",
  "location": "Karlsruhe",
  "email": null,
  "hireable": null,
  "bio": null,
  "twitter_username": null,
  "public_repos": 18,
  "public_gists": 0,
  "followers": 1,
  "following": 2,
  "created_at": "2022-07-05T08:31:56Z",
  "updated_at": "2024-02-27T13:54:43Z"
}