{
  "login": "peeta567",
  "id": 51520813,
  "node_id": "MDQ6VXNlcjUxNTIwODEz",
  "avatar_url": "https://avatars.githubusercontent.com/u/51520813?v=4",
  "gravatar_id": "",
  "url": "https://api.github.com/users/peeta567",
  "html_url": "https://github.com/peeta567",
  "followers_url": "https://api.github.com/users/peeta567/followers",
  "following_url": "https://api.github.com/users/peeta567/following{/other_user}",
  "gists_url": "https://api.github.com/users/peeta567/gists{/gist_id}",
  "starred_url": "https://api.github.com/users/peeta567/starred{/owner}{/repo}",
  "subscriptions_url": "https://api.github.com/users/peeta567/subscriptions",
  "organizations_url": "https://api.github.com/users/peeta567/orgs",
  "repos_url": "https://api.github.com/users/peeta567/repos",
  "events_url": "https://api.github.com/users/peeta567/events{/privacy}",
  "received_events_url": "https://api.github.com/users/peeta567/received_events",
  "type": "User",
  "user_view_type": "public",
  "site_admin": false,
  "name": null,
  "company": null,
  "blog": "",
  "location": null,
  "email": null,
  "hireable": null,
  "bio": null,
  "twitter_username": null,
  "public_repos": 2,
  "public_gists": 0,
  "followers": 0,
  "following": 0,
  "created_at": "2019-06-09T00:21:28Z",
  "updated_at": "2022-11-20T08:13:17Z"
}