{
  "login": "Pomarancz789",
  "id": 94035478,
  "node_id": "U_kgDOBZreFg",
  "avatar_url": "https://avatars.githubusercontent.com/u/94035478?v=4",
  "gravatar_id": "",
  "url": "https://api.github.com/users/Pomarancz789",
  "html_url": "https://github.com/Pomarancz789",
  "followers_url": "https://api.github.com/users/Pomarancz789/followers",
  "following_url": "https://api.github.com/users/Pomarancz789/following{/other_user}",
  "gists_url": "https://api.github.com/users/Pomarancz789/gists{/gist_id}",
  "starred_url": "https://api.github.com/users/Pomarancz789/starred{/owner}{/repo}",
  "subscriptions_url": "https://api.github.com/users/Pomarancz789/subscriptions",
  "organizations_url": "https://api.github.com/users/Pomarancz789/orgs",
  "repos_url": "https://api.github.com/users/Pomarancz789/repos",
  "events_url": "https://api.github.com/users/Pomarancz789/events{/privacy}",
  "received_events_url": "https://api.github.com/users/Pomarancz789/received_events",
  "type": "User",
  "user_view_type": "public",
  "site_admin": false,
  "name": null,
  "company": null,
  "blog": "",
  "location": null,
  "email": null,
  "hireable": null,
  "bio": null,
  "twitter_username": null,
  "public_repos": 27,
  "public_gists": 0,
  "followers": 3,
  "following": 2,
  "created_at": "2021-11-10T05:54:42Z",
  "updated_at": "2024-08-17T12:27:44Z"
}