{
  "login": "przemyslaw-pawelczak",
  "id": 9348927,
  "node_id": "MDQ6VXNlcjkzNDg5Mjc=",
  "avatar_url": "https://avatars.githubusercontent.com/u/9348927?v=4",
  "gravatar_id": "",
  "url": "https://api.github.com/users/przemyslaw-pawelczak",
  "html_url": "https://github.com/przemyslaw-pawelczak",
  "followers_url": "https://api.github.com/users/przemyslaw-pawelczak/followers",
  "following_url": "https://api.github.com/users/przemyslaw-pawelczak/following{/other_user}",
  "gists_url": "https://api.github.com/users/przemyslaw-pawelczak/gists{/gist_id}",
  "starred_url": "https://api.github.com/users/przemyslaw-pawelczak/starred{/owner}{/repo}",
  "subscriptions_url": "https://api.github.com/users/przemyslaw-pawelczak/subscriptions",
  "organizations_url": "https://api.github.com/users/przemyslaw-pawelczak/orgs",
  "repos_url": "https://api.github.com/users/przemyslaw-pawelczak/repos",
  "events_url": "https://api.github.com/users/przemyslaw-pawelczak/events{/privacy}",
  "received_events_url": "https://api.github.com/users/przemyslaw-pawelczak/received_events",
  "type": "User",
  "user_view_type": "public",
  "site_admin": false,
  "name": "Przemys\u0142aw Pawe\u0142czak",
  "company": "TU Delft",
  "blog": "http://www.pawelczak.net",
  "location": "Delft, The Netherlands",
  "email": "p.pawelczak@tudelft.nl",
  "hireable": null,
  "bio": "Associate Professor at TU Delft Embedded and Networked Systems Group",
  "twitter_username": "przemyslawp",
  "public_repos": 9,
  "public_gists": 0,
  "followers": 20,
  "following": 4,
  "created_at": "2014-10-22T08:51:09Z",
  "updated_at": "2024-10-12T11:24:45Z"
}