{
  "login": "qdevqt1",
  "id": 43266289,
  "node_id": "MDQ6VXNlcjQzMjY2Mjg5",
  "avatar_url": "https://avatars.githubusercontent.com/u/43266289?v=4",
  "gravatar_id": "",
  "url": "https://api.github.com/users/qdevqt1",
  "html_url": "https://github.com/qdevqt1",
  "followers_url": "https://api.github.com/users/qdevqt1/followers",
  "following_url": "https://api.github.com/users/qdevqt1/following{/other_user}",
  "gists_url": "https://api.github.com/users/qdevqt1/gists{/gist_id}",
  "starred_url": "https://api.github.com/users/qdevqt1/starred{/owner}{/repo}",
  "subscriptions_url": "https://api.github.com/users/qdevqt1/subscriptions",
  "organizations_url": "https://api.github.com/users/qdevqt1/orgs",
  "repos_url": "https://api.github.com/users/qdevqt1/repos",
  "events_url": "https://api.github.com/users/qdevqt1/events{/privacy}",
  "received_events_url": "https://api.github.com/users/qdevqt1/received_events",
  "type": "User",
  "user_view_type": "public",
  "site_admin": false,
  "name": null,
  "company": null,
  "blog": "",
  "location": null,
  "email": null,
  "hireable": null,
  "bio": null,
  "twitter_username": null,
  "public_repos": 3,
  "public_gists": 0,
  "followers": 0,
  "following": 0,
  "created_at": "2018-09-14T08:50:14Z",
  "updated_at": "2020-12-07T09:32:23Z"
}