{
  "login": "qrcworkshop",
  "id": 92785167,
  "node_id": "U_kgDOBYfKDw",
  "avatar_url": "https://avatars.githubusercontent.com/u/92785167?v=4",
  "gravatar_id": "",
  "url": "https://api.github.com/users/qrcworkshop",
  "html_url": "https://github.com/qrcworkshop",
  "followers_url": "https://api.github.com/users/qrcworkshop/followers",
  "following_url": "https://api.github.com/users/qrcworkshop/following{/other_user}",
  "gists_url": "https://api.github.com/users/qrcworkshop/gists{/gist_id}",
  "starred_url": "https://api.github.com/users/qrcworkshop/starred{/owner}{/repo}",
  "subscriptions_url": "https://api.github.com/users/qrcworkshop/subscriptions",
  "organizations_url": "https://api.github.com/users/qrcworkshop/orgs",
  "repos_url": "https://api.github.com/users/qrcworkshop/repos",
  "events_url": "https://api.github.com/users/qrcworkshop/events{/privacy}",
  "received_events_url": "https://api.github.com/users/qrcworkshop/received_events",
  "type": "User",
  "user_view_type": "public",
  "site_admin": false,
  "name": null,
  "company": null,
  "blog": "",
  "location": null,
  "email": null,
  "hireable": null,
  "bio": null,
  "twitter_username": null,
  "public_repos": 1,
  "public_gists": 0,
  "followers": 0,
  "following": 0,
  "created_at": "2021-10-19T08:50:11Z",
  "updated_at": "2021-12-05T10:04:33Z"
}