{
  "login": "Raghav-Bell",
  "id": 83136390,
  "node_id": "MDQ6VXNlcjgzMTM2Mzkw",
  "avatar_url": "https://avatars.githubusercontent.com/u/83136390?v=4",
  "gravatar_id": "",
  "url": "https://api.github.com/users/Raghav-Bell",
  "html_url": "https://github.com/Raghav-Bell",
  "followers_url": "https://api.github.com/users/Raghav-Bell/followers",
  "following_url": "https://api.github.com/users/Raghav-Bell/following{/other_user}",
  "gists_url": "https://api.github.com/users/Raghav-Bell/gists{/gist_id}",
  "starred_url": "https://api.github.com/users/Raghav-Bell/starred{/owner}{/repo}",
  "subscriptions_url": "https://api.github.com/users/Raghav-Bell/subscriptions",
  "organizations_url": "https://api.github.com/users/Raghav-Bell/orgs",
  "repos_url": "https://api.github.com/users/Raghav-Bell/repos",
  "events_url": "https://api.github.com/users/Raghav-Bell/events{/privacy}",
  "received_events_url": "https://api.github.com/users/Raghav-Bell/received_events",
  "type": "User",
  "user_view_type": "public",
  "site_admin": false,
  "name": "Raghav",
  "company": null,
  "blog": "https://raghav-bell.github.io/",
  "location": "India",
  "email": null,
  "hireable": null,
  "bio": "I am an autodidact, open source contributor, intrigued in finding answers to how, what and why.",
  "twitter_username": null,
  "public_repos": 27,
  "public_gists": 0,
  "followers": 3,
  "following": 0,
  "created_at": "2021-04-24T18:18:57Z",
  "updated_at": "2024-08-15T04:39:35Z"
}