{
  "login": "RatisWu",
  "id": 61738702,
  "node_id": "MDQ6VXNlcjYxNzM4NzAy",
  "avatar_url": "https://avatars.githubusercontent.com/u/61738702?v=4",
  "gravatar_id": "",
  "url": "https://api.github.com/users/RatisWu",
  "html_url": "https://github.com/RatisWu",
  "followers_url": "https://api.github.com/users/RatisWu/followers",
  "following_url": "https://api.github.com/users/RatisWu/following{/other_user}",
  "gists_url": "https://api.github.com/users/RatisWu/gists{/gist_id}",
  "starred_url": "https://api.github.com/users/RatisWu/starred{/owner}{/repo}",
  "subscriptions_url": "https://api.github.com/users/RatisWu/subscriptions",
  "organizations_url": "https://api.github.com/users/RatisWu/orgs",
  "repos_url": "https://api.github.com/users/RatisWu/repos",
  "events_url": "https://api.github.com/users/RatisWu/events{/privacy}",
  "received_events_url": "https://api.github.com/users/RatisWu/received_events",
  "type": "User",
  "site_admin": false,
  "name": null,
  "company": null,
  "blog": "",
  "location": "Taipei",
  "email": null,
  "hireable": null,
  "bio": null,
  "twitter_username": null,
  "public_repos": 12,
  "public_gists": 0,
  "followers": 2,
  "following": 0,
  "created_at": "2020-03-03T11:40:40Z",
  "updated_at": "2024-03-13T11:19:24Z"
}