{
  "login": "rganardi",
  "id": 28617619,
  "node_id": "MDQ6VXNlcjI4NjE3NjE5",
  "avatar_url": "https://avatars.githubusercontent.com/u/28617619?v=4",
  "gravatar_id": "",
  "url": "https://api.github.com/users/rganardi",
  "html_url": "https://github.com/rganardi",
  "followers_url": "https://api.github.com/users/rganardi/followers",
  "following_url": "https://api.github.com/users/rganardi/following{/other_user}",
  "gists_url": "https://api.github.com/users/rganardi/gists{/gist_id}",
  "starred_url": "https://api.github.com/users/rganardi/starred{/owner}{/repo}",
  "subscriptions_url": "https://api.github.com/users/rganardi/subscriptions",
  "organizations_url": "https://api.github.com/users/rganardi/orgs",
  "repos_url": "https://api.github.com/users/rganardi/repos",
  "events_url": "https://api.github.com/users/rganardi/events{/privacy}",
  "received_events_url": "https://api.github.com/users/rganardi/received_events",
  "type": "User",
  "user_view_type": "public",
  "site_admin": false,
  "name": "Ray Ganardi",
  "company": null,
  "blog": "ray.ganardi.xyz",
  "location": "Singapore, Singapore",
  "email": null,
  "hireable": true,
  "bio": null,
  "twitter_username": null,
  "public_repos": 11,
  "public_gists": 0,
  "followers": 3,
  "following": 1,
  "created_at": "2017-05-11T05:58:33Z",
  "updated_at": "2024-10-28T11:47:30Z"
}