{
  "login": "she-vidu",
  "id": 161282252,
  "node_id": "U_kgDOCZz4zA",
  "avatar_url": "https://avatars.githubusercontent.com/u/161282252?v=4",
  "gravatar_id": "",
  "url": "https://api.github.com/users/she-vidu",
  "html_url": "https://github.com/she-vidu",
  "followers_url": "https://api.github.com/users/she-vidu/followers",
  "following_url": "https://api.github.com/users/she-vidu/following{/other_user}",
  "gists_url": "https://api.github.com/users/she-vidu/gists{/gist_id}",
  "starred_url": "https://api.github.com/users/she-vidu/starred{/owner}{/repo}",
  "subscriptions_url": "https://api.github.com/users/she-vidu/subscriptions",
  "organizations_url": "https://api.github.com/users/she-vidu/orgs",
  "repos_url": "https://api.github.com/users/she-vidu/repos",
  "events_url": "https://api.github.com/users/she-vidu/events{/privacy}",
  "received_events_url": "https://api.github.com/users/she-vidu/received_events",
  "type": "User",
  "user_view_type": "public",
  "site_admin": false,
  "name": null,
  "company": null,
  "blog": "",
  "location": null,
  "email": null,
  "hireable": null,
  "bio": null,
  "twitter_username": null,
  "public_repos": 1,
  "public_gists": 0,
  "followers": 0,
  "following": 0,
  "created_at": "2024-02-26T05:54:07Z",
  "updated_at": "2024-04-03T20:37:37Z"
}