{
  "login": "stefanhannie",
  "id": 14877596,
  "node_id": "MDQ6VXNlcjE0ODc3NTk2",
  "avatar_url": "https://avatars.githubusercontent.com/u/14877596?v=4",
  "gravatar_id": "",
  "url": "https://api.github.com/users/stefanhannie",
  "html_url": "https://github.com/stefanhannie",
  "followers_url": "https://api.github.com/users/stefanhannie/followers",
  "following_url": "https://api.github.com/users/stefanhannie/following{/other_user}",
  "gists_url": "https://api.github.com/users/stefanhannie/gists{/gist_id}",
  "starred_url": "https://api.github.com/users/stefanhannie/starred{/owner}{/repo}",
  "subscriptions_url": "https://api.github.com/users/stefanhannie/subscriptions",
  "organizations_url": "https://api.github.com/users/stefanhannie/orgs",
  "repos_url": "https://api.github.com/users/stefanhannie/repos",
  "events_url": "https://api.github.com/users/stefanhannie/events{/privacy}",
  "received_events_url": "https://api.github.com/users/stefanhannie/received_events",
  "type": "User",
  "user_view_type": "public",
  "site_admin": false,
  "name": "Stefan Hannie",
  "company": "@AbCellera",
  "blog": "",
  "location": "Vancouver, BC",
  "email": "stefan.hannie@gmail.com",
  "hireable": null,
  "bio": "Studying the graphs that are lurking in reality. ",
  "twitter_username": null,
  "public_repos": 5,
  "public_gists": 1,
  "followers": 6,
  "following": 7,
  "created_at": "2015-09-28T18:11:48Z",
  "updated_at": "2024-09-03T15:32:07Z"
}