{
  "login": "stevefan1999",
  "id": 43277437,
  "node_id": "MDQ6VXNlcjQzMjc3NDM3",
  "avatar_url": "https://avatars.githubusercontent.com/u/43277437?v=4",
  "gravatar_id": "",
  "url": "https://api.github.com/users/stevefan1999",
  "html_url": "https://github.com/stevefan1999",
  "followers_url": "https://api.github.com/users/stevefan1999/followers",
  "following_url": "https://api.github.com/users/stevefan1999/following{/other_user}",
  "gists_url": "https://api.github.com/users/stevefan1999/gists{/gist_id}",
  "starred_url": "https://api.github.com/users/stevefan1999/starred{/owner}{/repo}",
  "subscriptions_url": "https://api.github.com/users/stevefan1999/subscriptions",
  "organizations_url": "https://api.github.com/users/stevefan1999/orgs",
  "repos_url": "https://api.github.com/users/stevefan1999/repos",
  "events_url": "https://api.github.com/users/stevefan1999/events{/privacy}",
  "received_events_url": "https://api.github.com/users/stevefan1999/received_events",
  "type": "User",
  "user_view_type": "public",
  "site_admin": false,
  "name": "Steve Fan",
  "company": "Hong Kong Polytechnic University",
  "blog": "",
  "location": "Hong Kong",
  "email": "19037626d@connect.polyu.hk",
  "hireable": null,
  "bio": "This is my official account",
  "twitter_username": null,
  "public_repos": 14,
  "public_gists": 0,
  "followers": 12,
  "following": 30,
  "created_at": "2018-09-14T16:49:33Z",
  "updated_at": "2023-10-10T02:11:24Z"
}