{
  "login": "tungbq",
  "id": 85242618,
  "node_id": "MDQ6VXNlcjg1MjQyNjE4",
  "avatar_url": "https://avatars.githubusercontent.com/u/85242618?v=4",
  "gravatar_id": "",
  "url": "https://api.github.com/users/tungbq",
  "html_url": "https://github.com/tungbq",
  "followers_url": "https://api.github.com/users/tungbq/followers",
  "following_url": "https://api.github.com/users/tungbq/following{/other_user}",
  "gists_url": "https://api.github.com/users/tungbq/gists{/gist_id}",
  "starred_url": "https://api.github.com/users/tungbq/starred{/owner}{/repo}",
  "subscriptions_url": "https://api.github.com/users/tungbq/subscriptions",
  "organizations_url": "https://api.github.com/users/tungbq/orgs",
  "repos_url": "https://api.github.com/users/tungbq/repos",
  "events_url": "https://api.github.com/users/tungbq/events{/privacy}",
  "received_events_url": "https://api.github.com/users/tungbq/received_events",
  "type": "User",
  "user_view_type": "public",
  "site_admin": false,
  "name": "Tung Leo",
  "company": "@TheDevOpsHub",
  "blog": "https://tungbq.github.io/tungbq/",
  "location": "Ho Chi Minh City, Vietnam",
  "email": "tung.bquang@gmail.com",
  "hireable": null,
  "bio": "DevOps Engineer \u2022 OpenSource \u2022 Cloud",
  "twitter_username": "tunggbui",
  "public_repos": 235,
  "public_gists": 0,
  "followers": 181,
  "following": 156,
  "created_at": "2021-06-02T15:04:23Z",
  "updated_at": "2024-10-19T09:49:43Z"
}