{
  "login": "wlivingston",
  "id": 12943773,
  "node_id": "MDQ6VXNlcjEyOTQzNzcz",
  "avatar_url": "https://avatars.githubusercontent.com/u/12943773?v=4",
  "gravatar_id": "",
  "url": "https://api.github.com/users/wlivingston",
  "html_url": "https://github.com/wlivingston",
  "followers_url": "https://api.github.com/users/wlivingston/followers",
  "following_url": "https://api.github.com/users/wlivingston/following{/other_user}",
  "gists_url": "https://api.github.com/users/wlivingston/gists{/gist_id}",
  "starred_url": "https://api.github.com/users/wlivingston/starred{/owner}{/repo}",
  "subscriptions_url": "https://api.github.com/users/wlivingston/subscriptions",
  "organizations_url": "https://api.github.com/users/wlivingston/orgs",
  "repos_url": "https://api.github.com/users/wlivingston/repos",
  "events_url": "https://api.github.com/users/wlivingston/events{/privacy}",
  "received_events_url": "https://api.github.com/users/wlivingston/received_events",
  "type": "User",
  "user_view_type": "public",
  "site_admin": false,
  "name": null,
  "company": null,
  "blog": "",
  "location": null,
  "email": null,
  "hireable": null,
  "bio": null,
  "twitter_username": null,
  "public_repos": 0,
  "public_gists": 0,
  "followers": 0,
  "following": 0,
  "created_at": "2015-06-17T22:55:55Z",
  "updated_at": "2024-09-13T18:57:35Z"
}