{
  "login": "YuChenSSR",
  "id": 55662670,
  "node_id": "MDQ6VXNlcjU1NjYyNjcw",
  "avatar_url": "https://avatars.githubusercontent.com/u/55662670?v=4",
  "gravatar_id": "",
  "url": "https://api.github.com/users/YuChenSSR",
  "html_url": "https://github.com/YuChenSSR",
  "followers_url": "https://api.github.com/users/YuChenSSR/followers",
  "following_url": "https://api.github.com/users/YuChenSSR/following{/other_user}",
  "gists_url": "https://api.github.com/users/YuChenSSR/gists{/gist_id}",
  "starred_url": "https://api.github.com/users/YuChenSSR/starred{/owner}{/repo}",
  "subscriptions_url": "https://api.github.com/users/YuChenSSR/subscriptions",
  "organizations_url": "https://api.github.com/users/YuChenSSR/orgs",
  "repos_url": "https://api.github.com/users/YuChenSSR/repos",
  "events_url": "https://api.github.com/users/YuChenSSR/events{/privacy}",
  "received_events_url": "https://api.github.com/users/YuChenSSR/received_events",
  "type": "User",
  "user_view_type": "public",
  "site_admin": false,
  "name": "ychen  ",
  "company": null,
  "blog": "",
  "location": null,
  "email": null,
  "hireable": null,
  "bio": "none",
  "twitter_username": null,
  "public_repos": 137,
  "public_gists": 40,
  "followers": 0,
  "following": 5,
  "created_at": "2019-09-22T15:32:20Z",
  "updated_at": "2024-10-27T11:54:41Z"
}