{
  "login": "Zikun97",
  "id": 33893392,
  "node_id": "MDQ6VXNlcjMzODkzMzky",
  "avatar_url": "https://avatars.githubusercontent.com/u/33893392?v=4",
  "gravatar_id": "",
  "url": "https://api.github.com/users/Zikun97",
  "html_url": "https://github.com/Zikun97",
  "followers_url": "https://api.github.com/users/Zikun97/followers",
  "following_url": "https://api.github.com/users/Zikun97/following{/other_user}",
  "gists_url": "https://api.github.com/users/Zikun97/gists{/gist_id}",
  "starred_url": "https://api.github.com/users/Zikun97/starred{/owner}{/repo}",
  "subscriptions_url": "https://api.github.com/users/Zikun97/subscriptions",
  "organizations_url": "https://api.github.com/users/Zikun97/orgs",
  "repos_url": "https://api.github.com/users/Zikun97/repos",
  "events_url": "https://api.github.com/users/Zikun97/events{/privacy}",
  "received_events_url": "https://api.github.com/users/Zikun97/received_events",
  "type": "User",
  "user_view_type": "public",
  "site_admin": false,
  "name": "Zhikun Wang",
  "company": null,
  "blog": "",
  "location": null,
  "email": null,
  "hireable": null,
  "bio": null,
  "twitter_username": null,
  "public_repos": 6,
  "public_gists": 0,
  "followers": 9,
  "following": 12,
  "created_at": "2017-11-22T08:52:34Z",
  "updated_at": "2024-09-14T02:28:44Z"
}